keygenfish/UniqueKeyGenerator.py
keygenfish/__init__.py
keygenfish-0.6.dist-info/METADATA
keygenfish-0.6.dist-info/WHEEL
keygenfish-0.6.dist-info/top_level.txt
keygenfish-0.6.dist-info/RECORD
